archon/__init__.py
archon/analyse_trades.py
archon/arch.py
archon/balances.py
archon/bittrex.py
archon/broker.py
archon/cryptopia.py
archon/mail.py
archon/markets.py
archon/order.py
archon/rex.py
archon/tx.py
archon/util.py
archon/warehouse.py
archon1-0.0.1.dist-info/METADATA
archon1-0.0.1.dist-info/RECORD
archon1-0.0.1.dist-info/WHEEL
archon1-0.0.1.dist-info/top_level.txt
