Metadata-Version: 2.1
Name: archon1
Version: 0.0.1
Summary: Trading agent framework
Home-page: http://pypi.python.org/pypi/archon1/
Author: Ben
Author-email: ben@enet.io
License: LICENSE
Platform: UNKNOWN
